PhpJiaochengCYuyanBianchengWangFix1/README.md
PhpJiaochengCYuyanBianchengWangFix1/__init__.py
PhpJiaochengCYuyanBianchengWangFix1/__main__.py
PhpJiaochengCYuyanBianchengWangFix1/file.epub
PhpJiaochengCYuyanBianchengWangFix1/index.html
PhpJiaochengCYuyanBianchengWangFix1/css/__init__.py
PhpJiaochengCYuyanBianchengWangFix1/css/annotations.css
PhpJiaochengCYuyanBianchengWangFix1/css/main.css
PhpJiaochengCYuyanBianchengWangFix1/css/normalize.css
PhpJiaochengCYuyanBianchengWangFix1/css/popup.css
PhpJiaochengCYuyanBianchengWangFix1/font/__init__.py
PhpJiaochengCYuyanBianchengWangFix1/font/fontello.eot
PhpJiaochengCYuyanBianchengWangFix1/font/fontello.svg
PhpJiaochengCYuyanBianchengWangFix1/font/fontello.ttf
PhpJiaochengCYuyanBianchengWangFix1/font/fontello.woff
PhpJiaochengCYuyanBianchengWangFix1/img/__init__.py
PhpJiaochengCYuyanBianchengWangFix1/img/annotator-glyph-sprite.png
PhpJiaochengCYuyanBianchengWangFix1/img/annotator-icon-sprite.png
PhpJiaochengCYuyanBianchengWangFix1/img/apple-touch-icon.png
PhpJiaochengCYuyanBianchengWangFix1/img/cancelfullscreen.png
PhpJiaochengCYuyanBianchengWangFix1/img/close.png
PhpJiaochengCYuyanBianchengWangFix1/img/fullscreen.png
PhpJiaochengCYuyanBianchengWangFix1/img/loader.gif
PhpJiaochengCYuyanBianchengWangFix1/img/menu-icon.png
PhpJiaochengCYuyanBianchengWangFix1/img/save.png
PhpJiaochengCYuyanBianchengWangFix1/img/saved.png
PhpJiaochengCYuyanBianchengWangFix1/img/settings-s.png
PhpJiaochengCYuyanBianchengWangFix1/img/settings.png
PhpJiaochengCYuyanBianchengWangFix1/img/star.png
PhpJiaochengCYuyanBianchengWangFix1/js/__init__.py
PhpJiaochengCYuyanBianchengWangFix1/js/epub.js
PhpJiaochengCYuyanBianchengWangFix1/js/epub.min.js
PhpJiaochengCYuyanBianchengWangFix1/js/epub.min.map
PhpJiaochengCYuyanBianchengWangFix1/js/hooks.min.js
PhpJiaochengCYuyanBianchengWangFix1/js/hooks.min.map
PhpJiaochengCYuyanBianchengWangFix1/js/reader.js
PhpJiaochengCYuyanBianchengWangFix1/js/reader.js.map
PhpJiaochengCYuyanBianchengWangFix1/js/reader.min.js
php_jiaocheng_c_yuyan_biancheng_wang_fix1-2025.3.24.1.dist-info/METADATA
php_jiaocheng_c_yuyan_biancheng_wang_fix1-2025.3.24.1.dist-info/WHEEL
php_jiaocheng_c_yuyan_biancheng_wang_fix1-2025.3.24.1.dist-info/entry_points.txt
php_jiaocheng_c_yuyan_biancheng_wang_fix1-2025.3.24.1.dist-info/top_level.txt
php_jiaocheng_c_yuyan_biancheng_wang_fix1-2025.3.24.1.dist-info/RECORD
